{
    "type": "FeatureCollection",
    "features": [
      {
        "type": "Feature",
        "geometry": {
          "type": "Point",
          "coordinates": [116.397428, 39.90923]
        },
        "properties": {
          "name": "北京测试油田",
          "type": "常规油田",
          "储量": 5000
        }
      }
    ]
  }